{
  "routes": [
    {
      "method": "GET",
      "path": "/bets",
      "handler": "bets.find",
      "config": {
        "policies": []
      }
    },
    {
      "method": "GET",
      "path": "/bets/count",
      "handler": "bets.count",
      "config": {
        "policies": []
      }
    },
    {
      "method": "GET",
      "path": "/bets/:id",
      "handler": "bets.findOne",
      "config": {
        "policies": []
      }
    },
    {
      "method": "POST",
      "path": "/bets",
      "handler": "bets.create",
      "config": {
        "policies": []
      }
    },
    {
      "method": "PUT",
      "path": "/bets/:id",
      "handler": "bets.update",
      "config": {
        "policies": []
      }
    },
    {
      "method": "DELETE",
      "path": "/bets/:id",
      "handler": "bets.delete",
      "config": {
        "policies": []
      }
    }
  ]
}
